fastaframes/__init__.py
fastaframes/fastaframes.py
fastaframes/util.py
fastaframes-1.2.2.dist-info/licenses/LICENSE
fastaframes-1.2.2.dist-info/METADATA
fastaframes-1.2.2.dist-info/WHEEL
fastaframes-1.2.2.dist-info/top_level.txt
fastaframes-1.2.2.dist-info/RECORD
