Metadata-Version: 2.4
Name: fastaframes
Version: 1.2.2
Summary: A very simple fasta file parser.
Author-email: Patrick Garrett <pgarrett@scripps.edu>
License: MIT License
Project-URL: repository, https://github.com/pgarrett-scripps/FastaFrames.git
Keywords: Fasta,Pandas,DataFrame
Classifier: Programming Language :: Python :: 3
Classifier: Development Status :: 4 - Beta
Classifier: License :: OSI Approved :: MIT License
Classifier: Operating System :: OS Independent
Requires-Python: >=3.8
License-File: LICENSE
Requires-Dist: pandas
Dynamic: license-file
